.gitignore
.travis.yml
LICENSE
MANIFEST.in
README.rst
setup.py
demo/demo.py
demo/sample_data_core.pkl
demo/sample_data_edge.pkl
docs/Makefile
docs/make.bat
docs/build/doctrees/environment.pickle
docs/build/doctrees/gptools.doctree
docs/build/doctrees/gptools.kernel.doctree
docs/build/doctrees/index.doctree
docs/build/doctrees/modules.doctree
docs/build/html/.buildinfo
docs/build/html/genindex.html
docs/build/html/gptools.html
docs/build/html/gptools.kernel.html
docs/build/html/index.html
docs/build/html/modules.html
docs/build/html/np-modindex.html
docs/build/html/objects.inv
docs/build/html/py-modindex.html
docs/build/html/search.html
docs/build/html/searchindex.js
docs/build/html/_images/math/0024155eabfcd1190d07f9520b42da07cc573f98.png
docs/build/html/_images/math/15c0e5b01b2bdc6a5ed2eea279f4c2f2b7cfd70b.png
docs/build/html/_images/math/172e6dadffd9800e796f3f96a1e24ce2a1840f3a.png
docs/build/html/_images/math/2be7268c95610c46b5939dc92d48f8a5eea456ab.png
docs/build/html/_images/math/3e4706baa604e1794d41d43400ba7708395a055b.png
docs/build/html/_images/math/3f243899bc87ead4773f775f234b52af69f27836.png
docs/build/html/_images/math/57a710d686452bd0ecc177300d3e523c300445a3.png
docs/build/html/_images/math/57ff4ac903860e9b65cecd0a4d38e725be98ec86.png
docs/build/html/_images/math/5e1668792d162faf7f4c6f233fcf3fda1b4f8592.png
docs/build/html/_images/math/6555583597f0140ab50c633f415f7b24ae12ce8d.png
docs/build/html/_images/math/7198c11f22989d15f71fc60acc87c66017ea5e94.png
docs/build/html/_images/math/897470a282b6b85fa5221eacd41369b9a157f491.png
docs/build/html/_images/math/9ad99798ec4c38e165cf517cb9e02b1c9e824103.png
docs/build/html/_images/math/9c8517c8f741ce57640333495649385dd9f0c8cc.png
docs/build/html/_images/math/a6b81ac9039f9854754a5a0ccb8f93d66b4e3fec.png
docs/build/html/_images/math/afed7b6656e31605fbc89857f1260a9e62dda899.png
docs/build/html/_images/math/b339c4c45440f4de3adc6c7b8f87571841bed3c0.png
gptools.egg-info/PKG-INFO
gptools.egg-info/SOURCES.txt
gptools.egg-info/dependency_links.txt
gptools.egg-info/requires.txt
gptools.egg-info/top_level.txt
