Metadata-Version: 1.0
Name: gptools
Version: 0.2.3
Summary: Gaussian process regression with derivative constraints and predictions.
Home-page: https://github.com/markchil/gptools
Author: Mark Chilenski
Author-email: mark.chilenski@gmail.com
License: GPL
Platform: UNKNOWN
